MANIFEST.in
setup.cfg
setup.py
tty_radio/__init__.py
tty_radio/__main__.py
tty_radio/album.py
tty_radio/api.py
tty_radio/banner.py
tty_radio/color.py
tty_radio/index.html
tty_radio/radio.py
tty_radio/station.py
tty_radio/stream.py
tty_radio/test.py
tty_radio/ui.py
tty_radio.egg-info/PKG-INFO
tty_radio.egg-info/SOURCES.txt
tty_radio.egg-info/dependency_links.txt
tty_radio.egg-info/entry_points.txt
tty_radio.egg-info/requires.txt
tty_radio.egg-info/top_level.txt