Metadata-Version: 1.1
Name: tty-radio
Version: 1.1.2
Summary: Linux/OS X RESTful player for online radio streams, like SomaFM and WCPE. Comes with a terminal UI flavored with colors and ASCII art and web UI for remote management.
Home-page: https://github.com/rfarley3/radio
Author: Ryan Farley
Author-email: rfarley3@gmu.edu
License: UNKNOWN
Download-URL: https://github.com/rfarley3/radio/tarball/1.1.2
Keywords: radio,somafm,streaming,mpg123
Platform: UNKNOWN
